<annotation>
	<folder>images</folder>
	<filename>image1-16.jpg</filename>
	<path>C:\Users\Anaec\Documents\testOCR\images\image1-16.jpg</path>
	<source>
		<database>Unknown</database>
	</source>
	<size>
		<width>1653</width>
		<height>2338</height>
		<depth>1</depth>
	</size>
	<segmented>0</segmented>
	<object>
		<name>text</name>
		<pose>Unspecified</pose>
		<truncated>0</truncated>
		<difficult>0</difficult>
		<bndbox>
			<xmin>214</xmin>
			<ymin>192</ymin>
			<xmax>1514</xmax>
			<ymax>1172</ymax>
		</bndbox>
	</object>
	<object>
		<name>text</name>
		<pose>Unspecified</pose>
		<truncated>0</truncated>
		<difficult>0</difficult>
		<bndbox>
			<xmin>224</xmin>
			<ymin>1179</ymin>
			<xmax>1519</xmax>
			<ymax>2077</ymax>
		</bndbox>
	</object>
</annotation>
