<annotation>
	<folder>images</folder>
	<filename>image4-113.jpg</filename>
	<path>C:\Users\Anaec\Documents\testOCR\images\image4-113.jpg</path>
	<source>
		<database>Unknown</database>
	</source>
	<size>
		<width>1643</width>
		<height>2315</height>
		<depth>1</depth>
	</size>
	<segmented>0</segmented>
	<object>
		<name>text</name>
		<pose>Unspecified</pose>
		<truncated>0</truncated>
		<difficult>0</difficult>
		<bndbox>
			<xmin>154</xmin>
			<ymin>232</ymin>
			<xmax>1574</xmax>
			<ymax>607</ymax>
		</bndbox>
	</object>
	<object>
		<name>text</name>
		<pose>Unspecified</pose>
		<truncated>0</truncated>
		<difficult>0</difficult>
		<bndbox>
			<xmin>719</xmin>
			<ymin>635</ymin>
			<xmax>984</xmax>
			<ymax>702</ymax>
		</bndbox>
	</object>
	<object>
		<name>table</name>
		<pose>Unspecified</pose>
		<truncated>0</truncated>
		<difficult>0</difficult>
		<bndbox>
			<xmin>301</xmin>
			<ymin>732</ymin>
			<xmax>1576</xmax>
			<ymax>1392</ymax>
		</bndbox>
	</object>
</annotation>
